Workbook

Sheet Assumptions
C3: Personcare Pharmaceuticals Limited — Psyllium Husk Powder Project: Assumptions & Input Block
C4: Blue = hardcoded input from the case study. Black = calculated. Yellow = key judgement agreed by the group. Change ONLY blue cells.
C6: PROJECT & FINANCIAL PARAMETERS | D6: Input Value | E6: Remarks
C7: Project evaluation life (years) | D7: 9 | E7: Case: 9-year expected product life
C8: Tax depreciation life (years) | D8: 12 | E8: ATO effective life of equipment — NOT the 9-year project life
C9: Required rate of return (nominal, after tax) | D9: 0.18 | E9: Board's hurdle rate
C10: Company tax rate | D10: 0.3 | E10: Australian corporate rate
C11: General inflation applied Years 6-9 | D11: 0.025 | E11: Case: 2.5% p.a. from Year 6
C12: Wage escalation Years 2-5 | D12: 0.035 | E12: Enterprise agreement
C13: Wage escalation Years 6-9 | D13: 0.025 | E13: Reverts to general inflation
C14: Factory overhead (% of total sales) | D14: 0.18 | E14: Variable overhead on new product AND contract sales
C15: Variable costs saved on cannibalised tablets | D15: 0.3 | E15: Only 30% of lost tablet revenue is a true loss avoided
C17: CAPITAL OUTLAY (YEAR 0) | D17: (Year 0) Amount | E17: Remarks
C18: New equipment | D18: 1515000 | E18: Depreciable asset
C19: Building modifications | D19: 95000 | E19: Immediately deductible for tax
C20: Initial inventory (working capital) | D20: 195000 | E20: Recovered at end of project
C21: Equipment salvage value, end of Year 9 | D21: 240000 | E21: Sold below written-down value → tax saving on loss
C23: ANNUAL DRIVERS (Years 1-5 from case; Years 6-9 escalated by formula) | D23: Year 1 | F23: Year 2 | G23: Year 3 | H23: Year 4 | I23: Year 5 | J23: Year 6 | K23: Year 7 | L23: Year 8 | M23: Year 9
C24: New product sales revenue | D24: 1650000 | F24: 2250000 | G24: 2800000 | H24: 3350000 | I24: 3650000 | J24: =I24*(1+$D$11) -> 3741250 | K24: =J24*(1+$D$11) -> 3834781.2 | L24: =K24*(1+$D$11) -> 3930650.8 | M24: =L24*(1+$D$11) -> 4028917.1
C25: Contract manufacturing revenue | D25: 280000 | F25: 360000 | G25: 430000 | H25: 480000 | I25: 530000 | J25: =I25*(1+$D$11) -> 543250 | K25: =J25*(1+$D$11) -> 556831.25 | L25: =K25*(1+$D$11) -> 570752.03 | M25: =L25*(1+$D$11) -> 585020.83
C26: Raw materials — new product | D26: 460000 | F26: 620000 | G26: 760000 | H26: 900000 | I26: 990000 | J26: =I26*(1+$D$11) -> 1014750 | K26: =J26*(1+$D$11) -> 1040118.7 | L26: =K26*(1+$D$11) -> 1066121.7 | M26: =L26*(1+$D$11) -> 1092774.8
C27: Raw materials — contract manufacturing | D27: 75000 | F27: 93000 | G27: 110000 | H27: 125000 | I27: 138000 | J27: =I27*(1+$D$11) -> 141450 | K27: =J27*(1+$D$11) -> 144986.25 | L27: =K27*(1+$D$11) -> 148610.91 | M27: =L27*(1+$D$11) -> 152326.18
C28: Lost sales of existing tablet (gross revenue) | D28: 384300 | F28: 516600 | G28: 598500 | H28: 667800 | I28: 749700 | J28: =I28*(1+$D$11) -> 768442.5 | K28: =J28*(1+$D$11) -> 787653.56 | L28: =K28*(1+$D$11) -> 807344.9 | M28: =L28*(1+$D$11) -> 827528.52
C29: Factory wages | D29: 225000 | F29: =D29*(1+$D$12) -> 232875 | G29: =F29*(1+$D$12) -> 241025.62 | H29: =G29*(1+$D$12) -> 249461.52 | I29: =H29*(1+$D$12) -> 258192.68 | J29: =I29*(1+$D$13) -> 264647.49 | K29: =J29*(1+$D$13) -> 271263.68 | L29: =K29*(1+$D$13) -> 278045.27 | M29: =L29*(1+$D$13) -> 284996.4
C30: Advertising | D30: 410000 | F30: 410000 | G30: 280000 | H30: 210000 | I30: 180000 | J30: =I30 -> 180000 | K30: =I30 -> 180000 | L30: =I30 -> 180000 | M30: =I30 -> 180000
C31: Maintenance | D31: 0 | F31: 0 | G31: 19000 | H31: 35000 | I31: 52000 | J31: =I31*(1+$D$11) -> 53300 | K31: =J31*(1+$D$11) -> 54632.5 | L31: =K31*(1+$D$11) -> 55998.312 | M31: =L31*(1+$D$11) -> 57398.27
C32: Accounts receivable balance (year end) | D32: 212000 | F32: 278000 | G32: 355000 | H32: 418000 | I32: 455000 | J32: =I32*(1+$D$11) -> 466375 | K32: =J32*(1+$D$11) -> 478034.37 | L32: =K32*(1+$D$11) -> 489985.23 | M32: =L32*(1+$D$11) -> 502234.87
C34: SUNK COSTS — EXCLUDED FROM THE MODEL | D34: Amount | E34: Remarks
C35: Research and development already incurred | D35: 250000
C36: European market research trip | D36: 30000
C37: Trips to India | D37: 40000
C38: Legal expenses | D38: 12000
C39: Total sunk cost excluded | D39: =SUM(D35:D38) -> 332000 | E39: Already incurred and unavoidable — irrelevant to the accept/reject decision
C41: ALSO EXCLUDED: the $600,000 loan principal and interest (financing flows already priced into the 18% discount rate); accounting depreciation and amortisation of the building modification (non-cash).

Sheet Initial Investment
I15: Initial Investment Outlay (Year 0)
I16: Gross commitment vs. net Year 0 free cash flow. The tax deduction on building modifications is taken in Year 0 (group decision).
I18: Particulars | J18: Amount | K18: Remarks
I19: New equipment | J19: =Assumptions!$D$18 -> 1515000 | K19: Capitalised; depreciated over the 12-year tax life
I20: Building modifications | J20: =Assumptions!$D$19 -> 95000 | K20: Fully deductible in the year incurred
I21: Increase in inventory (working capital) | J21: =Assumptions!$D$20 -> 195000 | K21: Recovered in full at the end of Year 9
I22: Gross initial commitment | J22: =SUM(J19:J21) -> 1805000 | K22: This is NOT the Year 0 net free cash flow
I23: Less: tax saving on building modifications | J23: =Assumptions!$D$19*Assumptions!$D$10 -> 28500 | K23: $95,000 x 30% = $28,500. Recognised in Year 0.
I24: NET YEAR 0 FREE CASH FLOW | J24: =-(J22-J23) -> -1776500

Sheet Tax Depreciation
C15: Tax Depreciation & Terminal Value of Equipment
C16: Straight line over the 12-year TAX life, not the 9-year project life. Equipment is sold in Year 9 with book value remaining.
C18: Tax year | D18: 1 | E18: 2 | F18: 3 | G18: 4 | H18: 5 | I18: 6 | J18: 7 | K18: 8 | L18: 9 | M18: 10 | N18: 11 | O18: 12
C19: Opening written-down value | D19: =Assumptions!$D$18 -> 1515000 | E19: =D21 -> 1388750 | F19: =E21 -> 1262500 | G19: =F21 -> 1136250 | H19: =G21 -> 1010000 | I19: =H21 -> 883750 | J19: =I21 -> 757500 | K19: =J21 -> 631250 | L19: =K21 -> 505000 | ... O19: =N21 -> 126250
C20: Annual tax depreciation | D20: =-Assumptions!$D$18/Assumptions!$D$8 -> -126250 | E20: =-Assumptions!$D$18/Assumptions!$D$8 -> -126250 | F20: =-Assumptions!$D$18/Assumptions!$D$8 -> -126250 | G20: =-Assumptions!$D$18/Assumptions!$D$8 -> -126250 | H20: =-Assumptions!$D$18/Assumptions!$D$8 -> -126250 | I20: =-Assumptions!$D$18/Assumptions!$D$8 -> -126250 | J20: =-Assumptions!$D$18/Assumptions!$D$8 -> -126250 | K20: =-Assumptions!$D$18/Assumptions!$D$8 -> -126250 | ... O20: =-Assumptions!$D$18/Assumptions!$D$8 -> -126250
C21: Closing written-down value | D21: =D19+D20 -> 1388750 | E21: =E19+E20 -> 1262500 | F21: =F19+F20 -> 1136250 | G21: =G19+G20 -> 1010000 | H21: =H19+H20 -> 883750 | I21: =I19+I20 -> 757500 | J21: =J19+J20 -> 631250 | K21: =K19+K20 -> 505000 | ... O21: =O19+O20 -> 0
C24: TERMINAL VALUE OF EQUIPMENT (END OF YEAR 9) | D24: Amount | E24: Remarks
C25: Written-down value at end of Year 9 | D25: =L21 -> 378750 | E25: Only 9 of the 12 tax years have elapsed
C26: Sale proceeds (salvage value) | D26: =Assumptions!$D$21 -> 240000 | E26: Case estimate
C27: Loss on disposal | D27: =D26-D25 -> -138750 | E27: Sold below written-down value
C28: Tax saving on the loss | D28: =-D27*Assumptions!$D$10 -> 41625 | E28: Loss is deductible at 30%
C29: NET AFTER-TAX SALVAGE (Year 9 inflow) | D29: =D26+D28 -> 281625 | E29: Flows into the Year 9 cash flow

Sheet Working Capital
F15: Working Capital
F16: Inventory is committed at Year 0. Receivables build with sales. The entire balance is released at the end of Year 9.
F18: Particulars | G18: Year 0 | H18: Year 1 | I18: Year 2 | J18: Year 3 | K18: Year 4 | L18: Year 5 | M18: Year 6 | N18: Year 7 | O18: Year 8 | P18: Year 9
F19: Accounts receivable balance | G19: 0 | H19: =Assumptions!D32 -> 212000 | I19: =Assumptions!F32 -> 278000 | J19: =Assumptions!G32 -> 355000 | K19: =Assumptions!H32 -> 418000 | L19: =Assumptions!I32 -> 455000 | M19: =Assumptions!J32 -> 466375 | N19: =Assumptions!K32 -> 478034.37 | O19: =Assumptions!L32 -> 489985.23 | P19: =Assumptions!M32 -> 502234.87
F20: Inventory balance | G20: =Assumptions!$D$20 -> 195000 | H20: =Assumptions!$D$20 -> 195000 | I20: =Assumptions!$D$20 -> 195000 | J20: =Assumptions!$D$20 -> 195000 | K20: =Assumptions!$D$20 -> 195000 | L20: =Assumptions!$D$20 -> 195000 | M20: =Assumptions!$D$20 -> 195000 | N20: =Assumptions!$D$20 -> 195000 | ... P20: =Assumptions!$D$20 -> 195000
F21: Total working capital balance | G21: =G19+G20 -> 195000 | H21: =H19+H20 -> 407000 | I21: =I19+I20 -> 473000 | J21: =J19+J20 -> 550000 | K21: =K19+K20 -> 613000 | L21: =L19+L20 -> 650000 | M21: =M19+M20 -> 661375 | N21: =N19+N20 -> 673034.37 | ... P21: =P19+P20 -> 697234.87
F22: Increase / (decrease) in working capital | G22: =G21 -> 195000 | H22: =H21-G21 -> 212000 | I22: =I21-H21 -> 66000 | J22: =J21-I21 -> 77000 | K22: =K21-J21 -> 63000 | L22: =L21-K21 -> 37000 | M22: =M21-L21 -> 11375 | N22: =N21-M21 -> 11659.375 | O22: =O21-N21 -> 11950.859 | P22: =P21-O21 -> 12249.631
F23: Cash flow impact (Years 1-9) | G23: n/a — in Initial Investment Outlay (Year 0) | H23: =-H22 -> -212000 | I23: =-I22 -> -66000 | J23: =-J22 -> -77000 | K23: =-K22 -> -63000 | L23: =-L22 -> -37000 | M23: =-M22 -> -11375 | N23: =-N22 -> -11659.375 | O23: =-O22 -> -11950.859 | P23: =-P22 -> -12249.631
F24: Working capital recovered at end of Year 9 | G24: =P21 -> 697234.87 | H24: Full closing balance released as the project winds up

Sheet Cash Flow Model
D3: Base-Case Net Free Cash Flow, Years 0 to 9
D4: Base case INCLUDES contract manufacturing revenue per management instruction. All figures nominal AUD; discounted at the 18% nominal hurdle rate.
D6: Particulars | E6: Year 0 | F6: Year 1 | G6: Year 2 | H6: Year 3 | I6: Year 4 | J6: Year 5 | K6: Year 6 | L6: Year 7 | M6: Year 8 | N6: Year 9
D7: REVENUE
D8: New product sales | F8: =Assumptions!D24 -> 1650000 | G8: =Assumptions!F24 -> 2250000 | H8: =Assumptions!G24 -> 2800000 | I8: =Assumptions!H24 -> 3350000 | J8: =Assumptions!I24 -> 3650000 | K8: =Assumptions!J24 -> 3741250 | L8: =Assumptions!K24 -> 3834781.2 | M8: =Assumptions!L24 -> 3930650.8 | N8: =Assumptions!M24 -> 4028917.1
D9: Contract manufacturing sales | F9: =Assumptions!D25 -> 280000 | G9: =Assumptions!F25 -> 360000 | H9: =Assumptions!G25 -> 430000 | I9: =Assumptions!H25 -> 480000 | J9: =Assumptions!I25 -> 530000 | K9: =Assumptions!J25 -> 543250 | L9: =Assumptions!K25 -> 556831.25 | M9: =Assumptions!L25 -> 570752.03 | N9: =Assumptions!M25 -> 585020.83
D10: Total revenue | F10: =SUM(F8:F9) -> 1930000 | G10: =SUM(G8:G9) -> 2610000 | H10: =SUM(H8:H9) -> 3230000 | I10: =SUM(I8:I9) -> 3830000 | J10: =SUM(J8:J9) -> 4180000 | K10: =SUM(K8:K9) -> 4284500 | L10: =SUM(L8:L9) -> 4391612.5 | M10: =SUM(M8:M9) -> 4501402.8 | N10: =SUM(N8:N9) -> 4613937.9
D11: OPERATING COSTS (incremental)
D12: Raw materials — new product | F12: =-Assumptions!D26 -> -460000 | G12: =-Assumptions!F26 -> -620000 | H12: =-Assumptions!G26 -> -760000 | I12: =-Assumptions!H26 -> -900000 | J12: =-Assumptions!I26 -> -990000 | K12: =-Assumptions!J26 -> -1014750 | L12: =-Assumptions!K26 -> -1040118.7 | M12: =-Assumptions!L26 -> -1066121.7 | N12: =-Assumptions!M26 -> -1092774.8
D13: Raw materials — contract manufacturing | F13: =-Assumptions!D27 -> -75000 | G13: =-Assumptions!F27 -> -93000 | H13: =-Assumptions!G27 -> -110000 | I13: =-Assumptions!H27 -> -125000 | J13: =-Assumptions!I27 -> -138000 | K13: =-Assumptions!J27 -> -141450 | L13: =-Assumptions!K27 -> -144986.25 | M13: =-Assumptions!L27 -> -148610.91 | N13: =-Assumptions!M27 -> -152326.18
D14: Cannibalisation of existing tablet (net) | F14: =-Assumptions!D28*(1-Assumptions!$D$15) -> -269010 | G14: =-Assumptions!F28*(1-Assumptions!$D$15) -> -361620 | H14: =-Assumptions!G28*(1-Assumptions!$D$15) -> -418950 | I14: =-Assumptions!H28*(1-Assumptions!$D$15) -> -467460 | J14: =-Assumptions!I28*(1-Assumptions!$D$15) -> -524790 | K14: =-Assumptions!J28*(1-Assumptions!$D$15) -> -537909.75 | L14: =-Assumptions!K28*(1-Assumptions!$D$15) -> -551357.49 | M14: =-Assumptions!L28*(1-Assumptions!$D$15) -> -565141.43 | N14: =-Assumptions!M28*(1-Assumptions!$D$15) -> -579269.97
D15: Factory wages | F15: =-Assumptions!D29 -> -225000 | G15: =-Assumptions!F29 -> -232875 | H15: =-Assumptions!G29 -> -241025.62 | I15: =-Assumptions!H29 -> -249461.52 | J15: =-Assumptions!I29 -> -258192.68 | K15: =-Assumptions!J29 -> -264647.49 | L15: =-Assumptions!K29 -> -271263.68 | M15: =-Assumptions!L29 -> -278045.27 | N15: =-Assumptions!M29 -> -284996.4
D16: Factory overhead (% of total sales) | F16: =-F10*Assumptions!$D$14 -> -347400 | G16: =-G10*Assumptions!$D$14 -> -469800 | H16: =-H10*Assumptions!$D$14 -> -581400 | I16: =-I10*Assumptions!$D$14 -> -689400 | J16: =-J10*Assumptions!$D$14 -> -752400 | K16: =-K10*Assumptions!$D$14 -> -771210 | L16: =-L10*Assumptions!$D$14 -> -790490.25 | M16: =-M10*Assumptions!$D$14 -> -810252.51 | N16: =-N10*Assumptions!$D$14 -> -830508.82
D17: Advertising | F17: =-Assumptions!D30 -> -410000 | G17: =-Assumptions!F30 -> -410000 | H17: =-Assumptions!G30 -> -280000 | I17: =-Assumptions!H30 -> -210000 | J17: =-Assumptions!I30 -> -180000 | K17: =-Assumptions!J30 -> -180000 | L17: =-Assumptions!K30 -> -180000 | M17: =-Assumptions!L30 -> -180000 | N17: =-Assumptions!M30 -> -180000
D18: Maintenance | F18: =-Assumptions!D31 -> 0 | G18: =-Assumptions!F31 -> 0 | H18: =-Assumptions!G31 -> -19000 | I18: =-Assumptions!H31 -> -35000 | J18: =-Assumptions!I31 -> -52000 | K18: =-Assumptions!J31 -> -53300 | L18: =-Assumptions!K31 -> -54632.5 | M18: =-Assumptions!L31 -> -55998.312 | N18: =-Assumptions!M31 -> -57398.27
D19: Total operating costs | F19: =SUM(F12:F18) -> -1786410 | G19: =SUM(G12:G18) -> -2187295 | H19: =SUM(H12:H18) -> -2410375.6 | I19: =SUM(I12:I18) -> -2676321.5 | J19: =SUM(J12:J18) -> -2895382.7 | K19: =SUM(K12:K18) -> -2963267.2 | L19: =SUM(L12:L18) -> -3032848.9 | M19: =SUM(M12:M18) -> -3104170.1 | N19: =SUM(N12:N18) -> -3177274.4
D20: EBITDA | F20: =F10+F19 -> 143590 | G20: =G10+G19 -> 422705 | H20: =H10+H19 -> 819624.38 | I20: =I10+I19 -> 1153678.5 | J20: =J10+J19 -> 1284617.3 | K20: =K10+K19 -> 1321232.8 | L20: =L10+L19 -> 1358763.6 | M20: =M10+M19 -> 1397232.7 | N20: =N10+N19 -> 1436663.5
D21: Tax depreciation | F21: ='Tax Depreciation'!D20 -> -126250 | G21: ='Tax Depreciation'!E20 -> -126250 | H21: ='Tax Depreciation'!F20 -> -126250 | I21: ='Tax Depreciation'!G20 -> -126250 | J21: ='Tax Depreciation'!H20 -> -126250 | K21: ='Tax Depreciation'!I20 -> -126250 | L21: ='Tax Depreciation'!J20 -> -126250 | M21: ='Tax Depreciation'!K20 -> -126250 | N21: ='Tax Depreciation'!L20 -> -126250
D22: EBIT | F22: =F20+F21 -> 17340 | G22: =G20+G21 -> 296455 | H22: =H20+H21 -> 693374.38 | I22: =I20+I21 -> 1027428.5 | J22: =J20+J21 -> 1158367.3 | K22: =K20+K21 -> 1194982.8 | L22: =L20+L21 -> 1232513.6 | M22: =M20+M21 -> 1270982.7 | N22: =N20+N21 -> 1310413.5
D23: Tax @ 30% | F23: =-F22*Assumptions!$D$10 -> -5202 | G23: =-G22*Assumptions!$D$10 -> -88936.5 | H23: =-H22*Assumptions!$D$10 -> -208012.31 | I23: =-I22*Assumptions!$D$10 -> -308228.54 | J23: =-J22*Assumptions!$D$10 -> -347510.2 | K23: =-K22*Assumptions!$D$10 -> -358494.83 | L23: =-L22*Assumptions!$D$10 -> -369754.07 | M23: =-M22*Assumptions!$D$10 -> -381294.8 | N23: =-N22*Assumptions!$D$10 -> -393124.04
D24: Net operating profit after tax | F24: =F22+F23 -> 12138 | G24: =G22+G23 -> 207518.5 | H24: =H22+H23 -> 485362.06 | I24: =I22+I23 -> 719199.93 | J24: =J22+J23 -> 810857.13 | K24: =K22+K23 -> 836487.93 | L24: =L22+L23 -> 862759.5 | M24: =M22+M23 -> 889687.87 | N24: =N22+N23 -> 917289.44
D25: Add back tax depreciation (non-cash) | F25: =-F21 -> 126250 | G25: =-G21 -> 126250 | H25: =-H21 -> 126250 | I25: =-I21 -> 126250 | J25: =-J21 -> 126250 | K25: =-K21 -> 126250 | L25: =-L21 -> 126250 | M25: =-M21 -> 126250 | N25: =-N21 -> 126250
D26: OPERATING CASH FLOW | F26: =F24+F25 -> 138388 | G26: =G24+G25 -> 333768.5 | H26: =H24+H25 -> 611612.06 | I26: =I24+I25 -> 845449.93 | J26: =J24+J25 -> 937107.13 | K26: =K24+K25 -> 962737.93 | L26: =L24+L25 -> 989009.5 | M26: =M24+M25 -> 1015937.9 | N26: =N24+N25 -> 1043539.4
D27: CAPITAL & TERMINAL FLOWS
D28: Initial investment outlay (net of tax saving) | E28: ='Initial Investment'!$J$24 -> -1776500 | F28: 0 | G28: 0 | H28: 0 | I28: 0 | J28: 0 | K28: 0 | L28: 0 | M28: 0 | N28: 0
D29: Change in working capital | F29: ='Working Capital'!H23 -> -212000 | G29: ='Working Capital'!I23 -> -66000 | H29: ='Working Capital'!J23 -> -77000 | I29: ='Working Capital'!K23 -> -63000 | J29: ='Working Capital'!L23 -> -37000 | K29: ='Working Capital'!M23 -> -11375 | L29: ='Working Capital'!N23 -> -11659.375 | M29: ='Working Capital'!O23 -> -11950.859 | N29: ='Working Capital'!P23 -> -12249.631
D30: Net after-tax salvage of equipment | E30: 0 | F30: 0 | G30: 0 | H30: 0 | I30: 0 | J30: 0 | K30: 0 | L30: 0 | M30: 0 | N30: ='Tax Depreciation'!$D$29 -> 281625
D31: Working capital recovered | E31: 0 | F31: 0 | G31: 0 | H31: 0 | I31: 0 | J31: 0 | K31: 0 | L31: 0 | M31: 0 | N31: ='Working Capital'!$G$24 -> 697234.87
D32: NET FREE CASH FLOW | E32: =SUM(E28:E31) -> -1776500 | F32: =F26+SUM(F28:F31) -> -73612 | G32: =G26+SUM(G28:G31) -> 267768.5 | H32: =H26+SUM(H28:H31) -> 534612.06 | I32: =I26+SUM(I28:I31) -> 782449.93 | J32: =J26+SUM(J28:J31) -> 900107.13 | K32: =K26+SUM(K28:K31) -> 951362.93 | L32: =L26+SUM(L28:L31) -> 977350.13 | M32: =M26+SUM(M28:M31) -> 1003987 | N32: =N26+SUM(N28:N31) -> 2010149.7
D33: Discount factor @ 18% | E33: =1/(1+Assumptions!$D$9)^0 -> 1 | F33: =1/(1+Assumptions!$D$9)^1 -> 0.84745763 | G33: =1/(1+Assumptions!$D$9)^2 -> 0.71818443 | H33: =1/(1+Assumptions!$D$9)^3 -> 0.60863087 | I33: =1/(1+Assumptions!$D$9)^4 -> 0.51578888 | J33: =1/(1+Assumptions!$D$9)^5 -> 0.43710922 | K33: =1/(1+Assumptions!$D$9)^6 -> 0.37043154 | L33: =1/(1+Assumptions!$D$9)^7 -> 0.31392503 | M33: =1/(1+Assumptions!$D$9)^8 -> 0.26603816 | N33: =1/(1+Assumptions!$D$9)^9 -> 0.22545607
D34: Present value of net free cash flow | E34: =E32*E33 -> -1776500 | F34: =F32*F33 -> -62383.051 | G34: =G32*G33 -> 192307.17 | H34: =H32*H33 -> 325381.41 | I34: =I32*I33 -> 403578.97 | J34: =J32*J33 -> 393445.12 | K34: =K32*K33 -> 352414.83 | L34: =L32*L33 -> 306814.67 | ... N34: =N32*N33 -> 453200.45
D35: Cumulative net free cash flow | E35: =E32 -> -1776500 | F35: =E35+F32 -> -1850112 | G35: =F35+G32 -> -1582343.5 | H35: =G35+H32 -> -1047731.4 | I35: =H35+I32 -> -265281.5 | J35: =I35+J32 -> 634825.62 | K35: =J35+K32 -> 1586188.6 | L35: =K35+L32 -> 2563538.7 | M35: =L35+M32 -> 3567525.7 | N35: =M35+N32 -> 5577675.4
D36: Cumulative discounted net free cash flow | E36: =E34 -> -1776500 | F36: =E36+F34 -> -1838883.1 | G36: =F36+G34 -> -1646575.9 | H36: =G36+H34 -> -1321194.5 | I36: =H36+I34 -> -917615.51 | J36: =I36+J34 -> -524170.38 | K36: =J36+K34 -> -171755.55 | L36: =K36+L34 -> 135059.12 | M36: =L36+M34 -> 402157.98 | N36: =M36+N34 -> 855358.43
D38: Note: Year 1 factory overhead and wages include the component attributable to contract manufacturing. Removing contract manufacturing (Section 4.1) requires stripping rows 7, 11, the contract share of row 14, and the $55,000 wage component in row 13.

Sheet Results
I15: Investment Decision Metrics (Base Case)
I16: MODEL FROZEN 12 August 2026. Every figure below is driven by formula from the Assumptions sheet.
I18: Metric | J18: Base case | K18: Interpretation
I19: Net present value at 18% | J19: =NPV(Assumptions!$D$9,'Cash Flow Model'!F32:N32)+'Cash Flow Model'!E32 -> 855358.43 | K19: Positive NPV — the project adds value at the Board’s hurdle rate
I20: Internal rate of return | J20: =IRR('Cash Flow Model'!E32:N32) -> 0.26452636 | K20: Compare against the 18% required return
I21: Profitability index | J21: =NPV(Assumptions!$D$9,'Cash Flow Model'!F32:N32)/-'Cash Flow Model'!E32 -> 1.4814852 | K21: PV of future flows per dollar of initial outlay
I22: Payback period (years) | J22: {=COUNTIF('Cash Flow Model'!F35:N35,"<0")+(-INDEX('Cash Flow Model'!F35:N35,1,COUNTIF('Cash Flow Model'!F35:N35,"<0"))/INDEX('Cash Flow Model'!F32:N32,1,COUNTIF('Cash Flow Model'!F35:N35,"<0")+1))} -> 4.2947221 | K22: Undiscounted — ignores the time value of money
I23: Discounted payback period (years) | J23: =COUNTIF('Cash Flow Model'!F36:N36,"<0")+(-INDEX('Cash Flow Model'!F36:N36,COUNTIF('Cash Flow Model'!F36:N36,"<0"))/INDEX('Cash Flow Model'!F34:N34,COUNTIF('Cash Flow Model'!F36:N36,"<0")+1)) -> 6.5598023 | K23: Against the 9-year project life
I25: RECONCILIATION CHECKS | J25: Amount | K25: Remarks
I26: Gross initial commitment | J26: ='Initial Investment'!$J$22 -> 1805000 | K26: Agrees to case: $1,515,000 + $95,000 + $195,000 = $1,805,000
I27: Net Year 0 free cash flow | J27: ='Cash Flow Model'!E32 -> -1776500 | K27: Gross commitment less the $28,500 building modification tax saving
I28: Net after-tax salvage, Year 9 | J28: ='Tax Depreciation'!$D$29 -> 281625 | K28: Target per work plan: $281,625
I29: Working capital recovered, Year 9 | J29: ='Working Capital'!$G$24 -> 697234.87 | K29: Target per work plan: ~$697,235
I30: Total sunk cost excluded | J30: =Assumptions!$D$39 -> 332000 | K30: Research, trips and legal fees — correctly outside the model
